{
  "format-version" : 2,
  "table-uuid" : "1780f485-bada-4a8b-b6fe-c20802f71c18",
  "location" : "spark-warehouse/iceberg/carro_iceberg",
  "last-sequence-number" : 3,
  "last-updated-ms" : 1745291768202,
  "last-column-id" : 5,
  "current-schema-id" : 1,
  "schemas" : [ {
    "type" : "struct",
    "schema-id" : 0,
    "fields" : [ {
      "id" : 1,
      "name" : "id",
      "required" : false,
      "type" : "int"
    }, {
      "id" : 2,
      "name" : "placa",
      "required" : false,
      "type" : "string"
    } ]
  }, {
    "type" : "struct",
    "schema-id" : 1,
    "fields" : [ {
      "id" : 1,
      "name" : "id",
      "required" : false,
      "type" : "int"
    }, {
      "id" : 2,
      "name" : "placa",
      "required" : false,
      "type" : "string"
    }, {
      "id" : 3,
      "name" : "marca",
      "required" : false,
      "type" : "string"
    }, {
      "id" : 4,
      "name" : "modelo",
      "required" : false,
      "type" : "string"
    }, {
      "id" : 5,
      "name" : "ano",
      "required" : false,
      "type" : "int"
    } ]
  } ],
  "default-spec-id" : 0,
  "partition-specs" : [ {
    "spec-id" : 0,
    "fields" : [ ]
  } ],
  "last-partition-id" : 999,
  "default-sort-order-id" : 0,
  "sort-orders" : [ {
    "order-id" : 0,
    "fields" : [ ]
  } ],
  "properties" : {
    "owner" : "Fontanella",
    "write.parquet.compression-codec" : "zstd"
  },
  "current-snapshot-id" : 6888732511390687745,
  "refs" : {
    "main" : {
      "snapshot-id" : 6888732511390687745,
      "type" : "branch"
    }
  },
  "snapshots" : [ {
    "sequence-number" : 1,
    "snapshot-id" : 6877570748610508183,
    "timestamp-ms" : 1745291755850,
    "summary" : {
      "operation" : "append",
      "spark.app.id" : "local-1745291725168",
      "added-data-files" : "3",
      "added-records" : "3",
      "added-files-size" : "1924",
      "changed-partition-count" : "1",
      "total-records" : "3",
      "total-files-size" : "1924",
      "total-data-files" : "3",
      "total-delete-files" : "0",
      "total-position-deletes" : "0",
      "total-equality-deletes" : "0",
      "engine-version" : "3.5.3",
      "app-id" : "local-1745291725168",
      "engine-name" : "spark",
      "iceberg-version" : "Apache Iceberg 1.6.1 (commit 8e9d59d299be42b0bca9461457cd1e95dbaad086)"
    },
    "manifest-list" : "spark-warehouse/iceberg/carro_iceberg/metadata/snap-6877570748610508183-1-ce2cb1be-8e99-439b-b76b-7f26bef4311d.avro",
    "schema-id" : 0
  }, {
    "sequence-number" : 2,
    "snapshot-id" : 4981980724280351416,
    "parent-snapshot-id" : 6877570748610508183,
    "timestamp-ms" : 1745291764860,
    "summary" : {
      "operation" : "overwrite",
      "spark.app.id" : "local-1745291725168",
      "added-data-files" : "1",
      "deleted-data-files" : "1",
      "added-records" : "1",
      "deleted-records" : "1",
      "added-files-size" : "1401",
      "removed-files-size" : "642",
      "changed-partition-count" : "1",
      "total-records" : "3",
      "total-files-size" : "2683",
      "total-data-files" : "3",
      "total-delete-files" : "0",
      "total-position-deletes" : "0",
      "total-equality-deletes" : "0",
      "engine-version" : "3.5.3",
      "app-id" : "local-1745291725168",
      "engine-name" : "spark",
      "iceberg-version" : "Apache Iceberg 1.6.1 (commit 8e9d59d299be42b0bca9461457cd1e95dbaad086)"
    },
    "manifest-list" : "spark-warehouse/iceberg/carro_iceberg/metadata/snap-4981980724280351416-1-7d45f7d5-806f-482f-92da-7fe24b4dffe0.avro",
    "schema-id" : 1
  }, {
    "sequence-number" : 3,
    "snapshot-id" : 6888732511390687745,
    "parent-snapshot-id" : 4981980724280351416,
    "timestamp-ms" : 1745291768202,
    "summary" : {
      "operation" : "overwrite",
      "spark.app.id" : "local-1745291725168",
      "added-data-files" : "1",
      "deleted-data-files" : "1",
      "added-records" : "1",
      "deleted-records" : "1",
      "added-files-size" : "1366",
      "removed-files-size" : "642",
      "changed-partition-count" : "1",
      "total-records" : "3",
      "total-files-size" : "3407",
      "total-data-files" : "3",
      "total-delete-files" : "0",
      "total-position-deletes" : "0",
      "total-equality-deletes" : "0",
      "engine-version" : "3.5.3",
      "app-id" : "local-1745291725168",
      "engine-name" : "spark",
      "iceberg-version" : "Apache Iceberg 1.6.1 (commit 8e9d59d299be42b0bca9461457cd1e95dbaad086)"
    },
    "manifest-list" : "spark-warehouse/iceberg/carro_iceberg/metadata/snap-6888732511390687745-1-e55f20bc-26aa-4e93-b27e-5aca4c575a34.avro",
    "schema-id" : 1
  } ],
  "statistics" : [ ],
  "partition-statistics" : [ ],
  "snapshot-log" : [ {
    "timestamp-ms" : 1745291755850,
    "snapshot-id" : 6877570748610508183
  }, {
    "timestamp-ms" : 1745291764860,
    "snapshot-id" : 4981980724280351416
  }, {
    "timestamp-ms" : 1745291768202,
    "snapshot-id" : 6888732511390687745
  } ],
  "metadata-log" : [ {
    "timestamp-ms" : 1745291730806,
    "metadata-file" : "spark-warehouse/iceberg/carro_iceberg/metadata/v1.metadata.json"
  }, {
    "timestamp-ms" : 1745291755850,
    "metadata-file" : "spark-warehouse/iceberg/carro_iceberg/metadata/v2.metadata.json"
  }, {
    "timestamp-ms" : 1745291760046,
    "metadata-file" : "spark-warehouse/iceberg/carro_iceberg/metadata/v3.metadata.json"
  }, {
    "timestamp-ms" : 1745291764860,
    "metadata-file" : "spark-warehouse/iceberg/carro_iceberg/metadata/v4.metadata.json"
  } ]
}